dcomputationaltool/__init__.py
dcomputationaltool/admin.py
dcomputationaltool/api.py
dcomputationaltool/apps.py
dcomputationaltool/models.py
dcomputationaltool/serializers.py
dcomputationaltool/urls.py
dcomputationaltool/views.py
dcomputationaltool/lib/__init__.py
dcomputationaltool/lib/computationaltools.py
dcomputationaltool/lib/gitlab.py
dcomputationaltool/tests/__init__.py
dcomputationaltool/tests/create_data.py
dcomputationaltool/tests/settings.py
dcomputationaltool/tests/test_models.py
dcomputationaltool/tests/test_response.py
dcomputationaltool/tests/urls.py
dcomputationaltool/tests/cwl/wc.stdout
dcomputationaltool/tests/cwl/wc_l.stdout
dcomputationaltool/tests/cwl/tools/echo.cwl
dcomputationaltool/tests/cwl/tools/star.cwl
dcomputationaltool/tests/cwl/tools/star.yml
dcomputationaltool/tests/cwl/tools/wc.cwl
dcomputationaltool/tests/cwl/workflows/count_letters.cwl
dcomputationaltool-0.0.2a3.dist-info/LICENSE
dcomputationaltool-0.0.2a3.dist-info/METADATA
dcomputationaltool-0.0.2a3.dist-info/WHEEL
dcomputationaltool-0.0.2a3.dist-info/top_level.txt
dcomputationaltool-0.0.2a3.dist-info/RECORD
