Metadata-Version: 2.1
Name: dcomputationaltool
Version: 0.0.2a3
Summary: UNKNOWN
Home-page: https://gitlab.com/r78v10a07/dcomputationaltool
Maintainer: Vera Alvarez, Roberto
Maintainer-email: veraalva@ncbi.nlm.nih.gov
License: Public Domain
Platform: UNKNOWN
Classifier: Development Status :: 3 - Alpha
Classifier: Environment :: Web Environment
Classifier: Framework :: Django :: 2.1
Classifier: Intended Audience :: Science/Research
Classifier: License :: Public Domain
Classifier: Natural Language :: English
Classifier: Operating System :: Unix
Classifier: Programming Language :: Python :: 3 :: Only
Classifier: Topic :: Scientific/Engineering :: Bio-Informatics
Requires-Dist: uWSGI (~=2.0.17)
Requires-Dist: Django (~=2.1)
Requires-Dist: django-appconf (~=1.0)
Requires-Dist: django-compressor (~=2.2)
Requires-Dist: django-filter (~=2.1)
Requires-Dist: djangorestframework (~=3.9)
Requires-Dist: settings-overrider (~=0.5)
Requires-Dist: urllib3 (~=1.24)
Requires-Dist: python-gitlab (~=1.7)
